eci/__init__.py
eci/py.typed
eci/utils.py
eci/enums/__init__.py
eci/enums/enums.py
eci/enums/message_ids.py
eci/interfaces/__init__.py
eci/interfaces/base_interface.py
eci/interfaces/covvi_interface.py
eci/interfaces/discovery.py
eci/interfaces/enums.py
eci/interfaces/messages.py
eci/interfaces/primitives.py
eci/interfaces/realtime.py
eci/interfaces/sockets.py
eci/interfaces/utils.py
eci/interfaces/control/__init__.py
eci/interfaces/control/base_control_interface.py
eci/interfaces/control/basic.py
eci/interfaces/control/control.py
eci/interfaces/control/digit.py
eci/interfaces/control/digit_config.py
eci/interfaces/control/direct_control.py
eci/interfaces/control/realtime_cfg.py
eci/interfaces/control/system_status.py
eci/interfaces/control/user_grip.py
eci/messages/__init__.py
eci/messages/base_control_message.py
eci/messages/base_message.py
eci/messages/bulk_message.py
eci/messages/control.py
eci/messages/control_message.py
eci/messages/discovery.py
eci/messages/enums.py
eci/messages/primitives.py
eci/messages/realtime.py
eci/messages/to_msg_cls.py
eci/messages/utils.py
eci/primitives/__init__.py
eci/primitives/base_primitive.py
eci/primitives/bulk_bytes.py
eci/primitives/command.py
eci/primitives/current_grip.py
eci/primitives/dtypes.py
eci/primitives/enums.py
eci/primitives/four_octet_address.py
eci/primitives/gripname.py
eci/primitives/hostname.py
eci/primitives/percentage.py
eci/primitives/product.py
eci/primitives/realtime_cfg.py
eci/primitives/six_octet_address.py
eci/primitives/speed.py
eci/sockets/__init__.py
eci/sockets/base_socket.py
eci/sockets/control.py
eci/sockets/enums.py
eci/sockets/messages.py
eci/sockets/primitives.py
eci/sockets/realtime.py
eci/sockets/discovery/__init__.py
eci/sockets/discovery/discovery_socket.py
eci/sockets/discovery/receiving.py
eci/sockets/discovery/sending.py
grips/__init__.py
grips/fist.gbc
grips/hook.gbc
grips/precision half.gbc
grips/ripple.gbc
grips/stick it.gbc
grips/thumbs up.gbc
grips/tripod closed.gbc
covvi_eci-1.1.6.dist-info/LICENSE.md
covvi_eci-1.1.6.dist-info/METADATA
covvi_eci-1.1.6.dist-info/WHEEL
covvi_eci-1.1.6.dist-info/top_level.txt
covvi_eci-1.1.6.dist-info/RECORD
