Metadata-Version: 2.2
Name: covvi-eci
Version: 1.1.6
Summary: This project provides the ethernet interface to the COVVI Hand.
Home-page: https://www.covvi-robotics.com/
Author: Jordan Birdsall
Author-email: jordan.birdsall@covvi.com
Maintainer: Jordan Birdsall
Maintainer-email: jordan.birdsall@covvi.com
Classifier: Operating System :: OS Independent
Classifier: Programming Language :: Python :: 3.13
Classifier: Programming Language :: Python :: 3.12
Classifier: Programming Language :: Python :: 3.11
Classifier: Programming Language :: Python :: 3.10
Classifier: Programming Language :: Python :: 3.9
Classifier: Programming Language :: Python :: 3.8
Requires-Python: >=3.8
License-File: LICENSE.md
Dynamic: author
Dynamic: author-email
Dynamic: classifier
Dynamic: description
Dynamic: description-content-type
Dynamic: home-page
Dynamic: maintainer
Dynamic: maintainer-email
Dynamic: requires-python
Dynamic: summary
